data_box/__init__.py
data_box/main_class.py
data_box/utilise.py
data_box-0.0.1.dist-info/DESCRIPTION.rst
data_box-0.0.1.dist-info/METADATA
data_box-0.0.1.dist-info/RECORD
data_box-0.0.1.dist-info/WHEEL
data_box-0.0.1.dist-info/metadata.json
data_box-0.0.1.dist-info/top_level.txt
