Metadata-Version: 2.0
Name: data-box
Version: 0.0.1
Summary: clean factor data
Home-page: UNKNOWN
Author: Yili Peng
Author-email: yili_peng@outlook.com
License: UNKNOWN
Platform: UNKNOWN
